dynamic_cli_builder/__init__.py
dynamic_cli_builder/__main__.py
dynamic_cli_builder/builder.py
dynamic_cli_builder/cli.py
dynamic_cli_builder/loader.py
dynamic_cli_builder/validators.py
dynamic_cli_builder-0.2.3.dist-info/LICENSE
dynamic_cli_builder-0.2.3.dist-info/METADATA
dynamic_cli_builder-0.2.3.dist-info/WHEEL
dynamic_cli_builder-0.2.3.dist-info/entry_points.txt
dynamic_cli_builder-0.2.3.dist-info/top_level.txt
dynamic_cli_builder-0.2.3.dist-info/RECORD
