Metadata-Version: 2.1
Name: dynamic-cli-builder
Version: 0.2.3
Summary: A Python library for dynamically building CLI tools from YAML configurations.
Home-page: UNKNOWN
Author: Idris Adigun
Author-email: adigun.idris@ymail.com
License: UNKNOWN
Platform: UNKNOWN
Classifier: Programming Language :: Python :: 3
Classifier: License :: OSI Approved :: MIT License
Classifier: Operating System :: OS Independent
Requires-Python: >=3.6
License-File: LICENSE
Requires-Dist: pyyaml
